pbj_tools/__init__.py
pbj_tools/functions.py
pbj_tools/main.py
pbj_tools-0.1.5.data/data/README.md
pbj_tools-0.1.5.dist-info/METADATA
pbj_tools-0.1.5.dist-info/WHEEL
pbj_tools-0.1.5.dist-info/entry_points.txt
pbj_tools-0.1.5.dist-info/top_level.txt
pbj_tools-0.1.5.dist-info/RECORD
