Metadata-Version: 2.1
Name: pbj-tools
Version: 0.1.5
Summary: Python package used to interact with phage.db
Home-page: https://github.com/JoshuaIszatt
Author: Joshua Iszatt
Author-email: joshiszatt@gmail.com
License: UNKNOWN
Platform: UNKNOWN
Requires-Python: >3
Requires-Dist: biopython (==1.83)
Requires-Dist: pandas (>=2.2.0)
